[
  {
    "id": "F101",
    "lat": 25.12815,
    "lon": 55.3441,
    "capacity": 2756,
    "efficiency": 86.6
  },
  {
    "id": "F102",
    "lat": 25.12232,
    "lon": 55.29733,
    "capacity": 1488,
    "efficiency": 50.3
  },
  {
    "id": "F103",
    "lat": 25.12949,
    "lon": 55.31406,
    "capacity": 2201,
    "efficiency": 76.2
  },
  {
    "id": "F104",
    "lat": 25.16701,
    "lon": 55.26884,
    "capacity": 2241,
    "efficiency": 96.3
  },
  {
    "id": "F105",
    "lat": 25.11496,
    "lon": 55.25745,
    "capacity": 4092,
    "efficiency": 52.1
  }
]